hydron/main.py
hydron-0.0.6.dist-info/licenses/LICENSE
hydron-0.0.6.dist-info/METADATA
hydron-0.0.6.dist-info/WHEEL
hydron-0.0.6.dist-info/top_level.txt
hydron-0.0.6.dist-info/RECORD
