Metadata-Version: 2.4
Name: hydron
Version: 0.0.6
Summary: Python interface for launching and post-processing SWMF magnetohydrodynamic simulations
Author-email: Sujay Shankar <sujays2001@gmail.com>
License-Expression: MIT
Project-URL: Repository, https://github.com/Sujay-Shankar/hydron
Project-URL: Issues, https://github.com/Sujay-Shankar/hydron/issues
Project-URL: Documentation, https://sujay-shankar.github.io/hydron
Project-URL: Releases, https://github.com/Sujay-Shankar/hydron/releases
Classifier: Programming Language :: Python :: 3.11
Classifier: Programming Language :: Python :: 3.12
Classifier: Programming Language :: Python :: 3.13
Classifier: Development Status :: 3 - Alpha
Requires-Python: >=3.11
License-File: LICENSE
Provides-Extra: test
Requires-Dist: pytest; extra == "test"
Provides-Extra: docs
Requires-Dist: mystmd; extra == "docs"
Dynamic: license-file
